<annotation>
	<folder>imgs</folder>
	<filename>vlc_extracted12401.jpg</filename>
	<path>/Volumes/HardDisk/CS599/imgs/vlc_extracted12401.jpg</path>
	<source>
		<database>Unknown</database>
	</source>
	<size>
		<width>960</width>
		<height>720</height>
		<depth>3</depth>
	</size>
	<segmented>0</segmented>
	<object>
		<name>terrorist</name>
		<pose>Unspecified</pose>
		<truncated>0</truncated>
		<difficult>0</difficult>
		<bndbox>
			<xmin>514</xmin>
			<ymin>377</ymin>
			<xmax>569</xmax>
			<ymax>475</ymax>
		</bndbox>
	</object>
</annotation>
